LICENSE.txt
README.md
pyproject.toml
optmagic/__init__.py
optmagic/argument.py
optmagic/pytest_action.py
optmagic.egg-info/PKG-INFO
optmagic.egg-info/SOURCES.txt
optmagic.egg-info/dependency_links.txt
optmagic.egg-info/requires.txt
optmagic.egg-info/top_level.txt