Metadata-Version: 2.4
Name: optmagic
Version: 1.1.1
Summary: Automatically make a command line interface from a python class or function.
Author-email: Lucas Sinclair <lucas.sinclair@me.com>
License: Copyright (c) 2026 Lucas Sinclair
Project-URL: Homepage, http://github.com/xapple/optmagic/
Requires-Python: >=3.8
License-File: LICENSE.txt
Requires-Dist: docstring_parser
Provides-Extra: tests
Requires-Dist: pytest; extra == "tests"
Dynamic: license-file
